{
  "1": {
    "message": "Vous vous trouvez dans le salle d'entrer",
    "messageA": "Aller voir la porte de gauche",
    "messageB": "Aller voir la porte du haut",
    "actionA": "/game/2",
    "actionB": "/game/3"
  },
  "2": {
    "message": "Vous vous trouvez dans un sallon et un Zombie et face à vous",
    "messageA": "Attaquer",
    "messageB": "faire demi-tour",
    "actionA": "/game/4",
    "actionB": "/game/1"
  },
  "3": {
    "message": "Vous essayez d'ouvrir la porte mais elle est fermée",
    "messageA": "faire demi-tour",
    "messageB": "",
    "actionA": "/game/1",
    "actionB": ""
  },
  "4": {
    "message": "Vous dégainez votre pistolet et tirez sur le Zombie. IL tombe à terre et ne semble pas se relever.",
    "messageA": "Fouiller son cadavre",
    "messageB": "Fouiller la salle",
    "messageC": "Faire demi-tour",
    "actionA": "/game/2",
    "actionB": "/game/6",
    "actionC": "/game/2",
    "key": "true",
    "nom": "fal"
  },
  "5": {
    "message": "Arrivée",
    "actionA": "/game/win",
    "messageA": "continuer",
    "actionB": ""
  },
  "6": {
    "message": "Piège mortelle",
    "actionA": "/game/lose",
    "messageA": "continuer",
    "actionB": ""
  },
  "7": {
    "message": "La porte est ouverte",
    "actionA": "/game/5",
    "messageA": "Entrer",
    "actionB": ""
  }
}


/*"1": {
  "message": "Game",
  "messageA": "Bienvenue !",
  "actions": [
    {
      "label": "allez a droite",
      "to": 2,
    },
    {
      "label": "allez a gauche",
      "to": 3,
    },
    {
      "label": "allez devant",
      "lose": true,
    },
  ]
}, */